nvidia/__init__.py
nvidia/cuda_runtime/__init__.py
nvidia/cuda_runtime/bin/__init__.py
nvidia/cuda_runtime/bin/cudart32_110.dll
nvidia/cuda_runtime/bin/cudart64_110.dll
nvidia/cuda_runtime/include/__init__.py
nvidia/cuda_runtime/include/builtin_types.h
nvidia/cuda_runtime/include/channel_descriptor.h
nvidia/cuda_runtime/include/common_functions.h
nvidia/cuda_runtime/include/cooperative_groups.h
nvidia/cuda_runtime/include/cuComplex.h
nvidia/cuda_runtime/include/cuda.h
nvidia/cuda_runtime/include/cudaD3D10.h
nvidia/cuda_runtime/include/cudaD3D10Typedefs.h
nvidia/cuda_runtime/include/cudaD3D11.h
nvidia/cuda_runtime/include/cudaD3D11Typedefs.h
nvidia/cuda_runtime/include/cudaD3D9.h
nvidia/cuda_runtime/include/cudaD3D9Typedefs.h
nvidia/cuda_runtime/include/cudaGL.h
nvidia/cuda_runtime/include/cudaGLTypedefs.h
nvidia/cuda_runtime/include/cudaProfilerTypedefs.h
nvidia/cuda_runtime/include/cudaTypedefs.h
nvidia/cuda_runtime/include/cuda_awbarrier.h
nvidia/cuda_runtime/include/cuda_awbarrier_helpers.h
nvidia/cuda_runtime/include/cuda_awbarrier_primitives.h
nvidia/cuda_runtime/include/cuda_bf16.h
nvidia/cuda_runtime/include/cuda_bf16.hpp
nvidia/cuda_runtime/include/cuda_d3d10_interop.h
nvidia/cuda_runtime/include/cuda_d3d11_interop.h
nvidia/cuda_runtime/include/cuda_d3d9_interop.h
nvidia/cuda_runtime/include/cuda_device_runtime_api.h
nvidia/cuda_runtime/include/cuda_egl_interop.h
nvidia/cuda_runtime/include/cuda_fp16.h
nvidia/cuda_runtime/include/cuda_fp16.hpp
nvidia/cuda_runtime/include/cuda_fp8.h
nvidia/cuda_runtime/include/cuda_fp8.hpp
nvidia/cuda_runtime/include/cuda_gl_interop.h
nvidia/cuda_runtime/include/cuda_occupancy.h
nvidia/cuda_runtime/include/cuda_pipeline.h
nvidia/cuda_runtime/include/cuda_pipeline_helpers.h
nvidia/cuda_runtime/include/cuda_pipeline_primitives.h
nvidia/cuda_runtime/include/cuda_runtime.h
nvidia/cuda_runtime/include/cuda_runtime_api.h
nvidia/cuda_runtime/include/cuda_surface_types.h
nvidia/cuda_runtime/include/cuda_texture_types.h
nvidia_cuda_runtime_cu11-11.8.89.dist-info/License.txt
nvidia_cuda_runtime_cu11-11.8.89.dist-info/METADATA
nvidia_cuda_runtime_cu11-11.8.89.dist-info/WHEEL
nvidia_cuda_runtime_cu11-11.8.89.dist-info/top_level.txt
nvidia_cuda_runtime_cu11-11.8.89.dist-info/RECORD
